{
    "swagger": "2.0",
    "info": {
        "contact": {}
    },
    "paths": {
        "/auth/login": {
            "post": {
                "description": "Authenticate user and return JWT token",
                "consumes": [
                    "application/json"
                ],
                "produces": [
                    "application/json"
                ],
                "tags": [
                    "Auth"
                ],
                "summary": "Login user",
                "parameters": [
                    {
                        "description": "User login credentials",
                        "name": "credentials",
                        "in": "body",
                        "required": true,
                        "schema": {
                            "$ref": "#/definitions/models.LoginRequest"
                        }
                    }
                ],
                "responses": {
                    "200": {
                        "description": "OK",
                        "schema": {
                            "type": "object",
                            "additionalProperties": {
                                "type": "string"
                            }
                        }
                    },
                    "400": {
                        "description": "Bad Request",
                        "schema": {
                            "type": "object",
                            "additionalProperties": {
                                "type": "string"
                            }
                        }
                    },
                    "401": {
                        "description": "Unauthorized",
                        "schema": {
                            "type": "object",
                            "additionalProperties": {
                                "type": "string"
                            }
                        }
                    },
                    "500": {
                        "description": "Internal Server Error",
                        "schema": {
                            "type": "object",
                            "additionalProperties": {
                                "type": "string"
                            }
                        }
                    }
                }
            }
        },
        "/auth/register": {
            "post": {
                "description": "Create a new user account",
                "consumes": [
                    "application/json"
                ],
                "produces": [
                    "application/json"
                ],
                "tags": [
                    "Auth"
                ],
                "summary": "Register a new user",
                "parameters": [
                    {
                        "description": "User Registration Request",
                        "name": "user",
                        "in": "body",
                        "required": true,
                        "schema": {
                            "$ref": "#/definitions/models.RegisterRequest"
                        }
                    }
                ],
                "responses": {
                    "201": {
                        "description": "Created",
                        "schema": {
                            "type": "object",
                            "additionalProperties": {
                                "type": "string"
                            }
                        }
                    },
                    "400": {
                        "description": "Bad Request",
                        "schema": {
                            "type": "object",
                            "additionalProperties": {
                                "type": "string"
                            }
                        }
                    },
                    "500": {
                        "description": "Internal Server Error",
                        "schema": {
                            "type": "object",
                            "additionalProperties": {
                                "type": "string"
                            }
                        }
                    }
                }
            }
        },
        "/transactions": {
            "get": {
                "security": [
                    {
                        "BearerAuth": []
                    }
                ],
                "description": "Retrieve all transactions for the authenticated user",
                "produces": [
                    "application/json"
                ],
                "tags": [
                    "Transactions"
                ],
                "summary": "Get all user transactions",
                "responses": {
                    "200": {
                        "description": "OK",
                        "schema": {
                            "type": "array",
                            "items": {
                                "$ref": "#/definitions/models.Transaction"
                            }
                        }
                    },
                    "500": {
                        "description": "Internal Server Error",
                        "schema": {
                            "type": "object",
                            "additionalProperties": {
                                "type": "string"
                            }
                        }
                    }
                }
            },
            "post": {
                "security": [
                    {
                        "BearerAuth": []
                    }
                ],
                "description": "Add a new income or expense transaction",
                "consumes": [
                    "application/json"
                ],
                "produces": [
                    "application/json"
                ],
                "tags": [
                    "Transactions"
                ],
                "summary": "Create a transaction",
                "parameters": [
                    {
                        "description": "Transaction to create",
                        "name": "transaction",
                        "in": "body",
                        "required": true,
                        "schema": {
                            "$ref": "#/definitions/models.Transaction"
                        }
                    },
                    {
                        "description": "Transaction to create",
                        "name": "transaction",
                        "in": "body",
                        "required": true,
                        "schema": {
                            "$ref": "#/definitions/dto.CreateTransactionInput"
                        }
                    }
                ],
                "responses": {
                    "200": {
                        "description": "OK",
                        "schema": {
                            "$ref": "#/definitions/models.Transaction"
                        }
                    },
                    "400": {
                        "description": "Bad Request",
                        "schema": {
                            "type": "object",
                            "additionalProperties": {
                                "type": "string"
                            }
                        }
                    },
                    "500": {
                        "description": "Internal Server Error",
                        "schema": {
                            "type": "object",
                            "additionalProperties": {
                                "type": "string"
                            }
                        }
                    }
                }
            }
        },
        "/transactions/balance": {
            "get": {
                "security": [
                    {
                        "BearerAuth": []
                    }
                ],
                "description": "Calculate and return total income, total expenses, and balance status (positive/negative)",
                "produces": [
                    "application/json"
                ],
                "tags": [
                    "Transactions"
                ],
                "summary": "Get current balance",
                "responses": {
                    "200": {
                        "description": "OK",
                        "schema": {
                            "type": "object",
                            "additionalProperties": true
                        }
                    },
                    "500": {
                        "description": "Internal Server Error",
                        "schema": {
                            "type": "object",
                            "additionalProperties": {
                                "type": "string"
                            }
                        }
                    }
                }
            }
        },
        "/transactions/{id}": {
            "put": {
                "security": [
                    {
                        "BearerAuth": []
                    }
                ],
                "description": "Update an existing transaction by ID for the authenticated user",
                "consumes": [
                    "application/json"
                ],
                "produces": [
                    "application/json"
                ],
                "tags": [
                    "Transactions"
                ],
                "summary": "Update a transaction",
                "parameters": [
                    {
                        "type": "string",
                        "description": "Transaction ID",
                        "name": "id",
                        "in": "path",
                        "required": true
                    },
                    {
                        "description": "Updated transaction data",
                        "name": "transaction",
                        "in": "body",
                        "required": true,
                        "schema": {
                            "$ref": "#/definitions/models.Transaction"
                        }
                    },
                    {
                        "description": "Updated transaction data",
                        "name": "transaction",
                        "in": "body",
                        "required": true,
                        "schema": {
                            "$ref": "#/definitions/dto.UpdateTransactionInput"
                        }
                    }
                ],
                "responses": {
                    "200": {
                        "description": "OK",
                        "schema": {
                            "$ref": "#/definitions/models.Transaction"
                        }
                    },
                    "400": {
                        "description": "Bad Request",
                        "schema": {
                            "type": "object",
                            "additionalProperties": {
                                "type": "string"
                            }
                        }
                    },
                    "404": {
                        "description": "Not Found",
                        "schema": {
                            "type": "object",
                            "additionalProperties": {
                                "type": "string"
                            }
                        }
                    },
                    "500": {
                        "description": "Internal Server Error",
                        "schema": {
                            "type": "object",
                            "additionalProperties": {
                                "type": "string"
                            }
                        }
                    }
                }
            },
            "delete": {
                "security": [
                    {
                        "BearerAuth": []
                    }
                ],
                "description": "Delete a transaction by ID for the authenticated user",
                "produces": [
                    "application/json"
                ],
                "tags": [
                    "Transactions"
                ],
                "summary": "Delete a transaction",
                "parameters": [
                    {
                        "type": "string",
                        "description": "Transaction ID",
                        "name": "id",
                        "in": "path",
                        "required": true
                    }
                ],
                "responses": {
                    "200": {
                        "description": "OK",
                        "schema": {
                            "type": "object",
                            "additionalProperties": {
                                "type": "string"
                            }
                        }
                    },
                    "404": {
                        "description": "Not Found",
                        "schema": {
                            "type": "object",
                            "additionalProperties": {
                                "type": "string"
                            }
                        }
                    },
                    "500": {
                        "description": "Internal Server Error",
                        "schema": {
                            "type": "object",
                            "additionalProperties": {
                                "type": "string"
                            }
                        }
                    }
                }
            }
        }
    },
    "definitions": {
        "dto.CreateTransactionInput": {
            "type": "object",
            "required": [
                "amount",
                "category",
                "type"
            ],
            "properties": {
                "amount": {
                    "type": "number"
                },
                "category": {
                    "type": "string"
                },
                "description": {
                    "type": "string"
                },
                "type": {
                    "type": "string",
                    "enum": [
                        "income",
                        "expense"
                    ]
                }
            }
        },
        "dto.UpdateTransactionInput": {
            "type": "object",
            "required": [
                "amount",
                "category",
                "type"
            ],
            "properties": {
                "amount": {
                    "type": "number"
                },
                "category": {
                    "type": "string"
                },
                "description": {
                    "type": "string"
                },
                "type": {
                    "type": "string",
                    "enum": [
                        "income",
                        "expense"
                    ]
                }
            }
        },
        "models.LoginRequest": {
            "type": "object",
            "required": [
                "email",
                "password"
            ],
            "properties": {
                "email": {
                    "type": "string",
                    "example": "somebody@someone.com"
                },
                "password": {
                    "type": "string",
                    "example": "password123"
                }
            }
        },
        "models.RegisterRequest": {
            "type": "object",
            "required": [
                "email",
                "name",
                "password"
            ],
            "properties": {
                "email": {
                    "type": "string",
                    "example": "somebody@someone.com"
                },
                "name": {
                    "type": "string",
                    "example": "Somebody Someone"
                },
                "password": {
                    "type": "string",
                    "minLength": 6,
                    "example": "password123"
                }
            }
        },
        "models.Transaction": {
            "type": "object",
            "required": [
                "amount",
                "category",
                "description",
                "type"
            ],
            "properties": {
                "amount": {
                    "type": "number"
                },
                "category": {
                    "type": "string",
                    "maxLength": 30,
                    "minLength": 2
                },
                "createdAt": {
                    "type": "string"
                },
                "date": {
                    "type": "string"
                },
                "description": {
                    "type": "string",
                    "minLength": 2
                },
                "id": {
                    "type": "integer"
                },
                "type": {
                    "description": "income or expense",
                    "type": "string",
                    "enum": [
                        "income",
                        "expense"
                    ]
                },
                "updatedAt": {
                    "type": "string"
                }
            }
        }
    },
    "securityDefinitions": {
        "BearerAuth": {
            "type": "apiKey",
            "name": "Authorization",
            "in": "header"
        }
    }
}